upldr-2.1.9.data/scripts/upldr
upldr_libs/__init__.py
upldr_libs/api/__init__.py
upldr_libs/api/main.py
upldr_libs/config_utils/__init__.py
upldr_libs/config_utils/config.py
upldr_libs/config_utils/loader.py
upldr_libs/get/__init__.py
upldr_libs/get/main.py
upldr_libs/get/remote_get.py
upldr_libs/gui/__init__.py
upldr_libs/gui/main.py
upldr_libs/libs/__init__.py
upldr_libs/libs/main.py
upldr_libs/put/__init__.py
upldr_libs/put/main.py
upldr_libs/put/put_api.py
upldr_libs/remote/__init__.py
upldr_libs/remote/main.py
upldr_libs/remote/remote_config.py
upldr_libs/s3/__init__.py
upldr_libs/s3/main.py
upldr_libs/search/__init__.py
upldr_libs/search/main.py
upldr_libs/serve/__init__.py
upldr_libs/serve/main.py
upldr_libs/serve/slave.py
upldr_libs/setup/__init__.py
upldr_libs/setup/main.py
upldr_libs/update/__init__.py
upldr_libs/update/main.py
upldr_libs/update/remote_indexes.py
upldr-2.1.9.dist-info/METADATA
upldr-2.1.9.dist-info/WHEEL
upldr-2.1.9.dist-info/top_level.txt
upldr-2.1.9.dist-info/RECORD
